dirlisting/__init__.py
dirlisting/__main__.py
dirlisting/cli.py
dirlisting/dirlisting.py
dirlisting-0.4.0.dist-info/entry_points.txt
dirlisting-0.4.0.dist-info/LICENSE
dirlisting-0.4.0.dist-info/WHEEL
dirlisting-0.4.0.dist-info/METADATA
dirlisting-0.4.0.dist-info/RECORD
