Metadata-Version: 2.1
Name: dirlisting
Version: 0.4.0
Summary: Create a directory listing diagram from text file
Home-page: https://github.com/yqbear/dirlisting/
License: MIT
Author: Stephan Poole
Requires-Python: >=3.9,<4.0
Classifier: License :: OSI Approved :: MIT License
Classifier: Programming Language :: Python :: 3
Classifier: Programming Language :: Python :: 3.10
Classifier: Programming Language :: Python :: 3.9
Requires-Dist: PyYAML (>=6.0,<7.0)
Requires-Dist: click (>=8.1.3,<9.0.0)
Project-URL: Documentation, https://dirlisting.readthedocs.io/en/latest/
Project-URL: Repository, https://github.com/yqbear/dirlisting/
